README.rst
setup.py
connectors/__init__.py
connectors/connectors.py
connectors.egg-info/PKG-INFO
connectors.egg-info/SOURCES.txt
connectors.egg-info/dependency_links.txt
connectors.egg-info/requires.txt
connectors.egg-info/top_level.txt
connectors/_common/__init__.py
connectors/_common/_event.py
connectors/_common/_executors.py
connectors/_common/_flags.py
connectors/_common/_input.py
connectors/_common/_multiinput_associate.py
connectors/_common/_multiinput_item.py
connectors/_common/_multioutput_item.py
connectors/_common/_non_lazy_inputs.py
connectors/_connectors/__init__.py
connectors/_connectors/_baseclasses.py
connectors/_connectors/_input.py
connectors/_connectors/_multiinput.py
connectors/_connectors/_multioutput.py
connectors/_connectors/_output.py
connectors/_decorators/__init__.py
connectors/_decorators/_baseclasses.py
connectors/_decorators/_input.py
connectors/_decorators/_multiinput.py
connectors/_decorators/_multioutput.py
connectors/_decorators/_output.py
connectors/_helper/__init__.py
connectors/_helper/_multiinputdata.py
connectors/_macro/__init__.py
connectors/_macro/_baseclass.py
connectors/_macro/_input.py
connectors/_macro/_output.py
connectors/_proxies/__init__.py
connectors/_proxies/_baseclasses.py
connectors/_proxies/_input.py
connectors/_proxies/_multiinput.py
connectors/_proxies/_multioutput.py
connectors/_proxies/_output.py
connectors/blocks/__init__.py
connectors/blocks/_multiplexer.py
connectors/blocks/_passthrough.py
connectors/blocks/_weakrefproxygenerator.py