Metadata-Version: 2.1
Name: connectors
Version: 4.0
Summary: A package for connecting objects to form a processing chain
Home-page: https://github.com/JonasSC/Connectors
Author: Jonas Schulte-Coerne
License: GNU Lesser General Public License v3 or later (LGPLv3+)
Project-URL: Documentation, https://connectors.readthedocs.io/en/latest/
Project-URL: Bug Reports, https://github.com/JonasSC/Connectors/issues
Project-URL: Source, https://github.com/JonasSC/Connectors
Keywords: parallel observer pipes-and-filters
Platform: UNKNOWN
Classifier: Development Status :: 5 - Production/Stable
Classifier: License :: OSI Approved :: GNU Lesser General Public License v3 or later (LGPLv3+)
Classifier: Programming Language :: Python :: 3.6
Classifier: Programming Language :: Python :: 3.7
Classifier: Intended Audience :: Developers
Classifier: Intended Audience :: Science/Research
Classifier: Topic :: Software Development :: Libraries :: Application Frameworks
Provides-Extra: dev
Provides-Extra: doc
Provides-Extra: test
